pyqt6_multiselect_combobox/__init__.py
pyqt6_multiselect_combobox/multiselect_combobox.py
pyqt6_multiselect_combobox-1.2.0.dist-info/licenses/LICENSE
pyqt6_multiselect_combobox-1.2.0.dist-info/METADATA
pyqt6_multiselect_combobox-1.2.0.dist-info/WHEEL
pyqt6_multiselect_combobox-1.2.0.dist-info/top_level.txt
pyqt6_multiselect_combobox-1.2.0.dist-info/RECORD
