Metadata-Version: 2.4
Name: pyqt6-multiselect-combobox
Version: 1.2.0
Summary: A custom PyQt6 widget providing a multi-select combobox functionality for PyQt6 applications.
Author: user0706
License: MIT
Project-URL: Homepage, https://github.com/user0706/pyqt6-multiselect-combobox
Project-URL: Issues, https://github.com/user0706/pyqt6-multiselect-combobox/issues
Project-URL: Documentation, https://pyqt6-multiselect-combobox.readthedocs.io/en/latest/
Keywords: PyQt6,Qt,combobox,multi-select,widget
Classifier: Development Status :: 5 - Production/Stable
Classifier: Intended Audience :: Developers
Classifier: License :: OSI Approved :: MIT License
Classifier: Programming Language :: Python
Classifier: Programming Language :: Python :: 3
Classifier: Programming Language :: Python :: 3 :: Only
Classifier: Programming Language :: Python :: 3.8
Classifier: Programming Language :: Python :: 3.9
Classifier: Programming Language :: Python :: 3.10
Classifier: Programming Language :: Python :: 3.11
Classifier: Programming Language :: Python :: 3.12
Classifier: Programming Language :: Python :: 3.13
Classifier: Operating System :: OS Independent
Classifier: Topic :: Software Development :: Libraries :: Python Modules
Requires-Python: >=3.8
License-File: LICENSE
Requires-Dist: PyQt6>=6.6.1
Dynamic: license-file
